cute.py
setup.py
cute.egg-info/PKG-INFO
cute.egg-info/SOURCES.txt
cute.egg-info/dependency_links.txt
cute.egg-info/top_level.txt