Metadata-Version: 1.0
Name: cute
Version: 0.0.1
Summary: cute egg
Home-page: https://github.com/CuteIO/cute-python-client
Author: liluo
Author-email: i@liluo.org
License: MIT License
Keywords: cute cute.io
Platform: any
